elevator_py-0.0.11.dist-info/licenses/LICENSE
elevator_saga/__init__.py
elevator_saga/client/__init__.py
elevator_saga/client/api_client.py
elevator_saga/client/base_controller.py
elevator_saga/client/proxy_models.py
elevator_saga/client_examples/__init__.py
elevator_saga/client_examples/bus_example.py
elevator_saga/client_examples/simple_example.py
elevator_saga/core/__init__.py
elevator_saga/core/models.py
elevator_saga/scripts/__init__.py
elevator_saga/scripts/client_examples/__init__.py
elevator_saga/scripts/client_examples/simple_example.py
elevator_saga/server/__init__.py
elevator_saga/server/simulator.py
elevator_saga/traffic/__init__.py
elevator_saga/traffic/down_peak.json
elevator_saga/traffic/fire_evacuation.json
elevator_saga/traffic/generators.py
elevator_saga/traffic/high_density.json
elevator_saga/traffic/inter_floor.json
elevator_saga/traffic/lunch_rush.json
elevator_saga/traffic/medical.json
elevator_saga/traffic/meeting_event.json
elevator_saga/traffic/mixed_scenario.json
elevator_saga/traffic/progressive_test.json
elevator_saga/traffic/random.json
elevator_saga/traffic/up_peak.json
elevator_saga/utils/__init__.py
elevator_saga/utils/logger.py
elevator_py-0.0.11.dist-info/METADATA
elevator_py-0.0.11.dist-info/WHEEL
elevator_py-0.0.11.dist-info/entry_points.txt
elevator_py-0.0.11.dist-info/top_level.txt
elevator_py-0.0.11.dist-info/RECORD
