Metadata-Version: 2.4
Name: elevator-py
Version: 0.0.11
Summary: Python implementation of Elevator Saga game with event system
Author-email: ZGCA-Forge Team <zgca@zgca.com>
License: MIT License
Project-URL: Homepage, https://github.com/ZGCA-Forge/Elevator
Project-URL: Documentation, https://zgca-forge.github.io/Elevator/
Project-URL: Repository, https://github.com/ZGCA-Forge/Elevator
Project-URL: Issues, https://github.com/ZGCA-Forge/Elevator/issues
Keywords: elevator,simulation,game,event-driven,optimization
Classifier: Development Status :: 4 - Beta
Classifier: Intended Audience :: Developers
Classifier: Intended Audience :: Education
Classifier: License :: OSI Approved :: MIT License
Classifier: Operating System :: OS Independent
Classifier: Programming Language :: Python :: 3
Classifier: Programming Language :: Python :: 3.10
Classifier: Programming Language :: Python :: 3.11
Classifier: Programming Language :: Python :: 3.12
Classifier: Programming Language :: Python :: 3.13
Classifier: Topic :: Games/Entertainment :: Simulation
Classifier: Topic :: Software Development :: Libraries :: Python Modules
Requires-Python: >=3.10
License-File: LICENSE
Requires-Dist: numpy>=1.20.0
Requires-Dist: quart>=0.19.0
Requires-Dist: hypercorn>=0.15.0
Provides-Extra: dev
Requires-Dist: pytest>=7.0.0; extra == "dev"
Requires-Dist: pytest-cov>=4.0.0; extra == "dev"
Requires-Dist: black>=22.0.0; extra == "dev"
Requires-Dist: isort>=5.0.0; extra == "dev"
Requires-Dist: mypy>=1.0.0; extra == "dev"
Requires-Dist: flake8>=6.0.0; extra == "dev"
Requires-Dist: pre-commit>=2.20.0; extra == "dev"
Requires-Dist: bump2version>=1.0.0; extra == "dev"
Provides-Extra: docs
Requires-Dist: sphinx>=5.0.0; extra == "docs"
Requires-Dist: sphinx-rtd-theme>=1.0.0; extra == "docs"
Requires-Dist: myst-parser>=0.18.0; extra == "docs"
Provides-Extra: all
Requires-Dist: elevatorpy[dev,docs]; extra == "all"
Dynamic: license-file
